strictjson/__init__.py
strictjson/parse_yaml.py
strictjson/legacy/strict_json.py
strictjson/legacy/strict_json_async.py
strictjson/utils/__init__.py
strictjson/utils/image_parser.py
strictjson-6.2.0.dist-info/LICENSE
strictjson-6.2.0.dist-info/METADATA
strictjson-6.2.0.dist-info/WHEEL
strictjson-6.2.0.dist-info/top_level.txt
strictjson-6.2.0.dist-info/RECORD
