Metadata-Version: 2.1
Name: strictjson
Version: 6.2.0
Summary: A Structured Output Framework for LLM Outputs
Author-email: John Tan Chong Min <tanchongmin@gmail.com>
License: Copyright (c) John's AI Group (discord.gg/bzp87AHJy5)
Project-URL: Homepage, https://github.com/tanchongmin/strictjson
Project-URL: Issues, https://github.com/tanchongmin/strictjson/issues
Classifier: Programming Language :: Python :: 3
Classifier: License :: OSI Approved :: MIT License
Classifier: Operating System :: OS Independent
Requires-Python: >=3.8
License-File: LICENSE
Requires-Dist: pydantic>=2.12.4
Requires-Dist: python-dotenv>=1.2.1
Requires-Dist: pyyaml>=6.0.3
